command.py
settings.py
vgrep/__init__.py
vgrep/contextualizer.py
vgrep/db.py
vgrep/file_interpreter.py
vgrep/file_sync.py
vgrep/fs.py
vgrep/manager.py
vgrep/query.py
vgrep/templater.py
vgrep/templates/__init__.py
vgrep/templates/contextualize.txt.j2
vgrep-0.1.4.dist-info/licenses/LICENSE
vgrep-0.1.4.dist-info/METADATA
vgrep-0.1.4.dist-info/WHEEL
vgrep-0.1.4.dist-info/entry_points.txt
vgrep-0.1.4.dist-info/top_level.txt
vgrep-0.1.4.dist-info/RECORD
