Metadata-Version: 2.4
Name: vgrep
Version: 0.1.4
Summary: Vector-based grep tool
License-Expression: GPL-3.0-only
Requires-Python: >=3.8
License-File: LICENSE
Requires-Dist: chromadb
Requires-Dist: jinja2
Requires-Dist: langchain-core
Requires-Dist: langchain-text-splitters
Requires-Dist: pydantic
Requires-Dist: pathspec
Dynamic: license-file
